muffin_babel/__init__.py
muffin_babel/py.typed
muffin_babel-1.7.0.dist-info/METADATA
muffin_babel-1.7.0.dist-info/WHEEL
muffin_babel-1.7.0.dist-info/RECORD
