Metadata-Version: 2.4
Name: muffin-babel
Version: 1.7.0
Summary: Localization support for the Muffin Framework
Project-URL: Homepage, https://github.com/klen/muffin-babel
Project-URL: Repository, https://github.com/klen/muffin-babel
Author-email: Kirill Klenov <horneds@gmail.com>
License-Expression: MIT
Keywords: asgi,asyncio,babel,internationalization,localization,muffin,trio
Classifier: Development Status :: 5 - Production/Stable
Classifier: Framework :: AsyncIO
Classifier: Framework :: Trio
Classifier: Intended Audience :: Developers
Classifier: License :: OSI Approved :: MIT License
Classifier: Programming Language :: Python
Classifier: Programming Language :: Python :: 3
Classifier: Programming Language :: Python :: 3.10
Classifier: Programming Language :: Python :: 3.11
Classifier: Programming Language :: Python :: 3.12
Classifier: Programming Language :: Python :: 3.13
Classifier: Programming Language :: Python :: 3.14
Classifier: Topic :: Internet :: WWW/HTTP
Requires-Python: <4,>=3.10
Requires-Dist: asgi-babel
Requires-Dist: muffin
